filesystem/__init__.py
filesystem/dataframe.py
filesystem/fmt/__init__.py
filesystem/fmt/audio.py
filesystem/fmt/base.py
filesystem/fmt/df.py
filesystem/fmt/img.py
filesystem/fmt/video.py
filesystem/io.py
filesystem/path.py
filesystem/reader.py
filesystem/stdin.py
filesystem_python-0.2.0.dist-info/LICENSE
filesystem_python-0.2.0.dist-info/WHEEL
filesystem_python-0.2.0.dist-info/METADATA
filesystem_python-0.2.0.dist-info/RECORD
