Metadata-Version: 2.1
Name: filesystem-python
Version: 0.2.0
Summary: FileSystem for Python
Home-page: https://github.com/kagemeka/filesystem-python/#readme
License: MIT
Keywords: template,python
Author: Hiroshi Tsuyuki
Author-email: kagemeka1@gmail.com
Maintainer: Hiroshi Tsuyuki
Maintainer-email: kagemeka1@gmail.com
Requires-Python: >=3.8,<3.11
Classifier: License :: OSI Approved :: MIT License
Classifier: Operating System :: OS Independent
Classifier: Programming Language :: Python :: 3
Classifier: Programming Language :: Python :: 3.10
Classifier: Programming Language :: Python :: 3.8
Classifier: Programming Language :: Python :: 3.9
Provides-Extra: docs
Requires-Dist: PyExcelerate
Requires-Dist: PyYAML
Requires-Dist: XlsxWriter
Requires-Dist: chardet
Requires-Dist: furo; extra == "docs"
Requires-Dist: h5py
Requires-Dist: iniconfig
Requires-Dist: myst-parser; extra == "docs"
Requires-Dist: openpyxl
Requires-Dist: optext-python (==0.1.1)
Requires-Dist: pdoc3; extra == "docs"
Requires-Dist: pydata-sphinx-theme; extra == "docs"
Requires-Dist: python-docs-theme; extra == "docs"
Requires-Dist: sphinx-book-theme; extra == "docs"
Requires-Dist: sphinx-theme-pd; extra == "docs"
Requires-Dist: sphinx; extra == "docs"
Requires-Dist: sphinx_rtd_theme (<=2.0.0); extra == "docs"
Requires-Dist: sphinxcontrib-mermaid; extra == "docs"
Requires-Dist: toml
Requires-Dist: untangle
Requires-Dist: xlrd (==1.2.0)
Requires-Dist: xmltodict
Project-URL: Documentation, https://filesystem-python.readthedocs.io
Project-URL: Repository, https://github.com/kagemeka/filesystem-python
